gssnng/__init__.py
gssnng/gene_sets.py
gssnng/score_cells.py
gssnng/score_funs.py
gssnng/smoothing.py
gssnng/util.py
gssnng-0.5.0.dist-info/METADATA
gssnng-0.5.0.dist-info/WHEEL
gssnng-0.5.0.dist-info/top_level.txt
gssnng-0.5.0.dist-info/RECORD
