Metadata-Version: 2.1
Name: gssnng
Version: 0.5.0
Summary: Gene Set Scoring on the Nearest Neighbor Graph (gssnng)
Home-page: http://github.com/gibbsdavidl/gssnng
Author: David Gibbs,Michael Strasser
Author-email: gibbsdavidl@gmail.com
License: MIT
Requires-Dist: pandas
Requires-Dist: numpy
Requires-Dist: matplotlib
Requires-Dist: seaborn
Requires-Dist: scipy
Requires-Dist: statsmodels
Requires-Dist: scanpy
Requires-Dist: tqdm
